sramongo/__init__.py
sramongo/bioproject.py
sramongo/biosample.py
sramongo/logger.py
sramongo/mongo.py
sramongo/mongo_schema.py
sramongo/pubmed.py
sramongo/sra.py
sramongo/sra2mongo.py
sramongo/sra_const.py
sramongo/xml_helpers.py
sramongo-0.0.3.dist-info/DESCRIPTION.rst
sramongo-0.0.3.dist-info/METADATA
sramongo-0.0.3.dist-info/RECORD
sramongo-0.0.3.dist-info/WHEEL
sramongo-0.0.3.dist-info/entry_points.txt
sramongo-0.0.3.dist-info/metadata.json
sramongo-0.0.3.dist-info/top_level.txt
