Metadata-Version: 2.0
Name: sramongo
Version: 0.0.3
Summary: A package to download metadata from SRA/Biosample/Geo and dump into a mongo database.
Home-page: https://github.com/jfear/sramongo
Author: Justin M Fear
Author-email: justin.m.fear@gmail.com
License: MIT license
Platform: UNKNOWN
Requires-Dist: biopython (>=1.68)
Requires-Dist: blinker (>=1.4)
Requires-Dist: mongoengine (>=0.11.0)
Requires-Dist: numpy (<=1.13.0)
Requires-Dist: pandas (>=0.19.2)
Requires-Dist: pymongo (>=3.3.0)
Requires-Dist: pytest (>=3.0.5)
Requires-Dist: setuptools (>=27.2.0)
Requires-Dist: sphinx (>=1.5.1)
Requires-Dist: sphinx-rtd-theme (>=0.1.9)
